setup.py
PlotDraw/__init__.py
PlotDraw/draw.py
PlotDraw/draw_helper.py
PlotDraw/reader.py
PlotDraw.egg-info/PKG-INFO
PlotDraw.egg-info/SOURCES.txt
PlotDraw.egg-info/dependency_links.txt
PlotDraw.egg-info/requires.txt
PlotDraw.egg-info/top_level.txt